moat/lib/gpio/__init__.py
moat/lib/gpio/gpio.py
moat/lib/gpio/test.py
moat_lib_gpio-0.9.3.dist-info/licenses/LICENSE.APACHE2
moat_lib_gpio-0.9.3.dist-info/licenses/LICENSE.MIT
moat_lib_gpio-0.9.3.dist-info/licenses/LICENSE.txt
moat_lib_gpio-0.9.3.dist-info/METADATA
moat_lib_gpio-0.9.3.dist-info/WHEEL
moat_lib_gpio-0.9.3.dist-info/top_level.txt
moat_lib_gpio-0.9.3.dist-info/RECORD
