Metadata-Version: 2.4
Name: moat-lib-gpio
Version: 0.9.3
Summary: Easy async access to GPIO pins
Author-email: Matthias Urlichs <matthias@urlichs.de>
Project-URL: homepage, https://m-o-a-t.org
Project-URL: repository, https://github.com/M-o-a-T/moat
Keywords: MoaT
Classifier: Intended Audience :: Developers
Classifier: Programming Language :: Python :: 3
Classifier: Framework :: AsyncIO
Classifier: Framework :: Trio
Classifier: Framework :: AnyIO
Classifier: Development Status :: 4 - Beta
Requires-Python: >=3.9
License-File: LICENSE.APACHE2
License-File: LICENSE.MIT
License-File: LICENSE.txt
Requires-Dist: anyio~=4.2
Requires-Dist: libgpiod~=2.2
Dynamic: license-file
